简单汇编语言的阅读
---

    public static void main(String[] args){
        ArrayList<Integer> list=new ArrayList<Integer>();
        list.add(0);
        ArrayList<Integer> arrayList=(ArrayList<Integer>)list.clone();
        list.set(0,1);
        System.out.println(list.get(0));
        System.out.println(arrayList.get(0));

    }

>用javap -c对代码进行反汇编
>
---
    public static void main(java.lang.String[]);
    Code:
       0: new           #2                  // class java/util/ArrayList
       3: dup
       4: invokespecial #3                  // Method java/util/ArrayList."<init>":()V
       7: astore_1
       8: aload_1
       9: iconst_0
      10: invokestatic  #4                  // Method java/lang/Integer.valueOf:(I)Ljava/lang/Integer;
      13: invokevirtual #5                  // Method java/util/ArrayList.add:(Ljava/lang/Object;)Z
      16: pop
      17: aload_1
      18: invokevirtual #6                  // Method java/util/ArrayList.clone:()Ljava/lang/Object;
      21: checkcast     #2                  // class java/util/ArrayList
      24: astore_2
      25: aload_1
      26: iconst_0
      27: iconst_1
      28: invokestatic  #4                  // Method java/lang/Integer.valueOf:(I)Ljava/lang/Integer;
      31: invokevirtual #7                  // Method java/util/ArrayList.set:(ILjava/lang/Object;)Ljava/lang/Object;
      34: pop
      35: getstatic     #8                  // Field java/lang/System.out:Ljava/io/PrintStream;
      38: aload_1
      39: iconst_0
      40: invokevirtual #9                  // Method java/util/ArrayList.get:(I)Ljava/lang/Object;
      43: invokevirtual #10                 // Method java/io/PrintStream.println:(Ljava/lang/Object;)V
      46: getstatic     #8                  // Field java/lang/System.out:Ljava/io/PrintStream;
      49: aload_2
      50: iconst_0
      51: invokevirtual #9                  // Method java/util/ArrayList.get:(I)Ljava/lang/Object;
      54: invokevirtual #10                 // Method java/io/PrintStream.println:(Ljava/lang/Object;)V
      57: return
- new的作用是创建指定类型的对象实例、对其进行默认初始化，并且将指向该实例的一个引用压入操作数栈顶，
- invokespecial调用实例构造方法<init>。
- astore_1用于将引用在本地保存。
- aload_1将引用压入栈顶。
- iconst_0将常量0压入栈中。
- invokestatic调用静态方法将常量0进行自动装箱。
- invokevirtual调用实例方法将常量放置到list当中，pop将list出栈。
- checkcast检查类型转换，检查未通过将抛出ClassCastException。








